dcae_cli/__init__.py
dcae_cli/_version.py
dcae_cli/cli.py
dcae_cli/conftest.py
dcae_cli/catalog/__init__.py
dcae_cli/catalog/exc.py
dcae_cli/catalog/mock/__init__.py
dcae_cli/catalog/mock/catalog.py
dcae_cli/catalog/mock/schema.py
dcae_cli/catalog/mock/tables.py
dcae_cli/commands/__init__.py
dcae_cli/commands/util.py
dcae_cli/commands/catalog/__init__.py
dcae_cli/commands/catalog/commands.py
dcae_cli/commands/component/__init__.py
dcae_cli/commands/component/commands.py
dcae_cli/commands/data_format/__init__.py
dcae_cli/commands/data_format/commands.py
dcae_cli/commands/profiles/__init__.py
dcae_cli/commands/profiles/commands.py
dcae_cli/util/__init__.py
dcae_cli/util/cdap_util.py
dcae_cli/util/config.py
dcae_cli/util/discovery.py
dcae_cli/util/dmaap.py
dcae_cli/util/docker_util.py
dcae_cli/util/exc.py
dcae_cli/util/inputs.py
dcae_cli/util/logger.py
dcae_cli/util/policy.py
dcae_cli/util/profiles.py
dcae_cli/util/run.py
dcae_cli/util/undeploy.py
onap_dcae_cli-2.11.4.dist-info/METADATA
onap_dcae_cli-2.11.4.dist-info/WHEEL
onap_dcae_cli-2.11.4.dist-info/entry_points.txt
onap_dcae_cli-2.11.4.dist-info/top_level.txt
onap_dcae_cli-2.11.4.dist-info/RECORD
